{
  "success": true,
  "base": "USD",
  "start_date": "2021-10-30",
  "end_date": "2022-10-29",
  "rates": {
    "2021-10-30": {
      "XAU": 0.00056084
    },
    "2021-10-31": {
      "XAU": 0.00056191
    },
    "2021-11-01": {
      "XAU": 0.00055792
    },
    "2021-11-02": {
      "XAU": 0.00055936
    },
    "2021-11-03": {
      "XAU": 0.00056361
    },
    "2021-11-04": {
      "XAU": 0.00055812
    },
    "2021-11-05": {
      "XAU": 0.00055018
    },
    "2021-11-06": {
      "XAU": 0.00055006
    },
    "2021-11-07": {
      "XAU": 0.0005508
    },
    "2021-11-08": {
      "XAU": 0.00054808
    },
    "2021-11-09": {
      "XAU": 0.00054649
    },
    "2021-11-10": {
      "XAU": 0.00054085
    },
    "2021-11-11": {
      "XAU": 0.00053704
    },
    "2021-11-12": {
      "XAU": 0.00053626
    },
    "2021-11-13": {
      "XAU": 0.00053616
    },
    "2021-11-14": {
      "XAU": 0.00053601
    },
    "2021-11-15": {
      "XAU": 0.0005368
    },
    "2021-11-16": {
      "XAU": 0.00054034
    },
    "2021-11-17": {
      "XAU": 0.00053578
    },
    "2021-11-18": {
      "XAU": 0.00053796
    },
    "2021-11-19": {
      "XAU": 0.00054194
    },
    "2021-11-20": {
      "XAU": 0.00054185
    },
    "2021-11-21": {
      "XAU": 0.00054201
    },
    "2021-11-22": {
      "XAU": 0.00055325
    },
    "2021-11-23": {
      "XAU": 0.00055874
    },
    "2021-11-24": {
      "XAU": 0.00055897
    },
    "2021-11-25": {
      "XAU": 0.00055839
    },
    "2021-11-26": {
      "XAU": 0.00055786
    },
    "2021-11-27": {
      "XAU": 0.00055793
    },
    "2021-11-28": {
      "XAU": 0.00055851
    },
    "2021-11-29": {
      "XAU": 0.00055729
    },
    "2021-11-30": {
      "XAU": 0.00056035
    },
    "2021-12-01": {
      "XAU": 0.00056451
    },
    "2021-12-02": {
      "XAU": 0.00056134
    },
    "2021-12-03": {
      "XAU": 0.0005655
    },
    "2021-12-04": {
      "XAU": 0.00056108
    },
    "2021-12-05": {
      "XAU": 0.00056142
    },
    "2021-12-06": {
      "XAU": 0.00056147
    },
    "2021-12-07": {
      "XAU": 0.00056129
    },
    "2021-12-08": {
      "XAU": 0.00056054
    },
    "2021-12-09": {
      "XAU": 0.00056006
    },
    "2021-12-10": {
      "XAU": 0.00056061
    },
    "2021-12-11": {
      "XAU": 0.00056087
    },
    "2021-12-12": {
      "XAU": 0.00056098
    },
    "2021-12-13": {
      "XAU": 0.00055989
    },
    "2021-12-14": {
      "XAU": 0.00055894
    },
    "2021-12-15": {
      "XAU": 0.00056413
    },
    "2021-12-16": {
      "XAU": 0.00056081
    },
    "2021-12-17": {
      "XAU": 0.00055589
    },
    "2021-12-18": {
      "XAU": 0.00055612
    },
    "2021-12-19": {
      "XAU": 0.0005562
    },
    "2021-12-20": {
      "XAU": 0.00055838
    },
    "2021-12-21": {
      "XAU": 0.00055865
    },
    "2021-12-22": {
      "XAU": 0.00055422
    },
    "2021-12-23": {
      "XAU": 0.00055284
    },
    "2021-12-24": {
      "XAU": 0.00055295
    },
    "2021-12-25": {
      "XAU": 0.00055098
    },
    "2021-12-26": {
      "XAU": 0.00055302
    },
    "2021-12-27": {
      "XAU": 0.00055197
    },
    "2021-12-28": {
      "XAU": 0.00055345
    },
    "2021-12-29": {
      "XAU": 0.00055427
    },
    "2021-12-30": {
      "XAU": 0.00055078
    },
    "2021-12-31": {
      "XAU": 0.00054672
    },
    "2022-01-01": {
      "XAU": 0.00054668
    },
    "2022-01-02": {
      "XAU": 0.00054658
    },
    "2022-01-03": {
      "XAU": 0.0005546
    },
    "2022-01-04": {
      "XAU": 0.00055146
    },
    "2022-01-05": {
      "XAU": 0.0005523
    },
    "2022-01-06": {
      "XAU": 0.00055838
    },
    "2022-01-07": {
      "XAU": 0.00055659
    },
    "2022-01-08": {
      "XAU": 0.00055647
    },
    "2022-01-09": {
      "XAU": 0.00055697
    },
    "2022-01-10": {
      "XAU": 0.00055511
    },
    "2022-01-11": {
      "XAU": 0.00054904
    },
    "2022-01-12": {
      "XAU": 0.00054901
    },
    "2022-01-13": {
      "XAU": 0.000549
    },
    "2022-01-14": {
      "XAU": 0.0005502
    },
    "2022-01-15": {
      "XAU": 0.0005502
    },
    "2022-01-16": {
      "XAU": 0.00055012
    },
    "2022-01-17": {
      "XAU": 0.00054993
    },
    "2022-01-18": {
      "XAU": 0.00055115
    },
    "2022-01-19": {
      "XAU": 0.00054366
    },
    "2022-01-20": {
      "XAU": 0.00054389
    },
    "2022-01-21": {
      "XAU": 0.00054516
    },
    "2022-01-22": {
      "XAU": 0.00054515
    },
    "2022-01-23": {
      "XAU": 0.00054448
    },
    "2022-01-24": {
      "XAU": 0.00054279
    },
    "2022-01-25": {
      "XAU": 0.00054091
    },
    "2022-01-26": {
      "XAU": 0.00054938
    },
    "2022-01-27": {
      "XAU": 0.00055623
    },
    "2022-01-28": {
      "XAU": 0.00055814
    },
    "2022-01-29": {
      "XAU": 0.00055814
    },
    "2022-01-30": {
      "XAU": 0.00055862
    },
    "2022-01-31": {
      "XAU": 0.00055628
    },
    "2022-02-01": {
      "XAU": 0.00055533
    },
    "2022-02-02": {
      "XAU": 0.00055609
    },
    "2022-02-03": {
      "XAU": 0.00055375
    },
    "2022-02-04": {
      "XAU": 0.00055324
    },
    "2022-02-05": {
      "XAU": 0.00055306
    },
    "2022-02-06": {
      "XAU": 0.00055257
    },
    "2022-02-07": {
      "XAU": 0.00054904
    },
    "2022-02-08": {
      "XAU": 0.00054928
    },
    "2022-02-09": {
      "XAU": 0.0005454
    },
    "2022-02-10": {
      "XAU": 0.00054748
    },
    "2022-02-11": {
      "XAU": 0.00053799
    },
    "2022-02-12": {
      "XAU": 0.00053807
    },
    "2022-02-13": {
      "XAU": 0.00053777
    },
    "2022-02-14": {
      "XAU": 0.00053687
    },
    "2022-02-15": {
      "XAU": 0.00053944
    },
    "2022-02-16": {
      "XAU": 0.00053494
    },
    "2022-02-17": {
      "XAU": 0.00052635
    },
    "2022-02-18": {
      "XAU": 0.00052684
    },
    "2022-02-19": {
      "XAU": 0.00052681
    },
    "2022-02-20": {
      "XAU": 0.00052517
    },
    "2022-02-21": {
      "XAU": 0.0005235
    },
    "2022-02-22": {
      "XAU": 0.00052651
    },
    "2022-02-23": {
      "XAU": 0.00052331
    },
    "2022-02-24": {
      "XAU": 0.00052314
    },
    "2022-02-25": {
      "XAU": 0.00052936
    },
    "2022-02-26": {
      "XAU": 0.00052919
    },
    "2022-02-27": {
      "XAU": 0.00052263
    },
    "2022-02-28": {
      "XAU": 0.00052432
    },
    "2022-03-01": {
      "XAU": 0.00051467
    },
    "2022-03-02": {
      "XAU": 0.00051829
    },
    "2022-03-03": {
      "XAU": 0.00051663
    },
    "2022-03-04": {
      "XAU": 0.00050761
    },
    "2022-03-05": {
      "XAU": 0.0005074
    },
    "2022-03-06": {
      "XAU": 0.00050269
    },
    "2022-03-07": {
      "XAU": 0.00050457
    },
    "2022-03-08": {
      "XAU": 0.00049767
    },
    "2022-03-09": {
      "XAU": 0.00050223
    },
    "2022-03-10": {
      "XAU": 0.00050047
    },
    "2022-03-11": {
      "XAU": 0.00050308
    },
    "2022-03-12": {
      "XAU": 0.00050297
    },
    "2022-03-13": {
      "XAU": 0.00050645
    },
    "2022-03-14": {
      "XAU": 0.00051173
    },
    "2022-03-15": {
      "XAU": 0.00052168
    },
    "2022-03-16": {
      "XAU": 0.00051887
    },
    "2022-03-17": {
      "XAU": 0.00051493
    },
    "2022-03-18": {
      "XAU": 0.00051433
    },
    "2022-03-19": {
      "XAU": 0.00052081
    },
    "2022-03-20": {
      "XAU": 0.00052126
    },
    "2022-03-21": {
      "XAU": 0.00051642
    },
    "2022-03-22": {
      "XAU": 0.0005206
    },
    "2022-03-23": {
      "XAU": 0.00051366
    },
    "2022-03-24": {
      "XAU": 0.0005105
    },
    "2022-03-25": {
      "XAU": 0.00051067
    },
    "2022-03-26": {
      "XAU": 0.00051075
    },
    "2022-03-27": {
      "XAU": 0.00051072
    },
    "2022-03-28": {
      "XAU": 0.00052007
    },
    "2022-03-29": {
      "XAU": 0.00052141
    },
    "2022-03-30": {
      "XAU": 0.00051757
    },
    "2022-03-31": {
      "XAU": 0.00051648
    },
    "2022-04-01": {
      "XAU": 0.00051945
    },
    "2022-04-02": {
      "XAU": 0.00051966
    },
    "2022-04-03": {
      "XAU": 0.00051985
    },
    "2022-04-04": {
      "XAU": 0.00051757
    },
    "2022-04-05": {
      "XAU": 0.00052032
    },
    "2022-04-06": {
      "XAU": 0.00052077
    },
    "2022-04-07": {
      "XAU": 0.0005175
    },
    "2022-04-08": {
      "XAU": 0.00051358
    },
    "2022-04-09": {
      "XAU": 0.00051353
    },
    "2022-04-10": {
      "XAU": 0.00051404
    },
    "2022-04-11": {
      "XAU": 0.00051201
    },
    "2022-04-12": {
      "XAU": 0.0005088
    },
    "2022-04-13": {
      "XAU": 0.00050537
    },
    "2022-04-14": {
      "XAU": 0.00050753
    },
    "2022-04-15": {
      "XAU": 0.00050701
    },
    "2022-04-16": {
      "XAU": 0.00050648
    },
    "2022-04-17": {
      "XAU": 0.0005051
    },
    "2022-04-18": {
      "XAU": 0.00050591
    },
    "2022-04-19": {
      "XAU": 0.00051312
    },
    "2022-04-20": {
      "XAU": 0.00051145
    },
    "2022-04-21": {
      "XAU": 0.00051225
    },
    "2022-04-22": {
      "XAU": 0.00051772
    },
    "2022-04-23": {
      "XAU": 0.00051769
    },
    "2022-04-24": {
      "XAU": 0.00051764
    },
    "2022-04-25": {
      "XAU": 0.00052665
    },
    "2022-04-26": {
      "XAU": 0.00052622
    },
    "2022-04-27": {
      "XAU": 0.00053058
    },
    "2022-04-28": {
      "XAU": 0.00052797
    },
    "2022-04-29": {
      "XAU": 0.00052716
    },
    "2022-04-30": {
      "XAU": 0.00052716
    },
    "2022-05-01": {
      "XAU": 0.00052668
    },
    "2022-05-02": {
      "XAU": 0.00053694
    },
    "2022-05-03": {
      "XAU": 0.00053509
    },
    "2022-05-04": {
      "XAU": 0.00052987
    },
    "2022-05-05": {
      "XAU": 0.00053281
    },
    "2022-05-06": {
      "XAU": 0.00053366
    },
    "2022-05-07": {
      "XAU": 0.00053108
    },
    "2022-05-08": {
      "XAU": 0.00053172
    },
    "2022-05-09": {
      "XAU": 0.0005392
    },
    "2022-05-10": {
      "XAU": 0.00054395
    },
    "2022-05-11": {
      "XAU": 0.00053956
    },
    "2022-05-12": {
      "XAU": 0.00054924
    },
    "2022-05-13": {
      "XAU": 0.00055204
    },
    "2022-05-14": {
      "XAU": 0.00055208
    },
    "2022-05-15": {
      "XAU": 0.00055198
    },
    "2022-05-16": {
      "XAU": 0.00054721
    },
    "2022-05-17": {
      "XAU": 0.00055129
    },
    "2022-05-18": {
      "XAU": 0.00055039
    },
    "2022-05-19": {
      "XAU": 0.00054227
    },
    "2022-05-20": {
      "XAU": 0.00054152
    },
    "2022-05-21": {
      "XAU": 0.00054153
    },
    "2022-05-22": {
      "XAU": 0.00054161
    },
    "2022-05-23": {
      "XAU": 0.00053926
    },
    "2022-05-24": {
      "XAU": 0.00053572
    },
    "2022-05-25": {
      "XAU": 0.00053959
    },
    "2022-05-26": {
      "XAU": 0.00053991
    },
    "2022-05-27": {
      "XAU": 0.0005397
    },
    "2022-05-28": {
      "XAU": 0.0005397
    },
    "2022-05-29": {
      "XAU": 0.00054053
    },
    "2022-05-30": {
      "XAU": 0.00053971
    },
    "2022-05-31": {
      "XAU": 0.00054414
    },
    "2022-06-01": {
      "XAU": 0.00054144
    },
    "2022-06-02": {
      "XAU": 0.00053499
    },
    "2022-06-03": {
      "XAU": 0.0005402
    },
    "2022-06-04": {
      "XAU": 0.00054037
    },
    "2022-06-05": {
      "XAU": 0.00053993
    },
    "2022-06-06": {
      "XAU": 0.00054364
    },
    "2022-06-07": {
      "XAU": 0.00054004
    },
    "2022-06-08": {
      "XAU": 0.00053937
    },
    "2022-06-09": {
      "XAU": 0.00054157
    },
    "2022-06-10": {
      "XAU": 0.00053441
    },
    "2022-06-11": {
      "XAU": 0.00053441
    },
    "2022-06-12": {
      "XAU": 0.00053309
    },
    "2022-06-13": {
      "XAU": 0.00054923
    },
    "2022-06-14": {
      "XAU": 0.00055259
    },
    "2022-06-15": {
      "XAU": 0.00054545
    },
    "2022-06-16": {
      "XAU": 0.00054011
    },
    "2022-06-17": {
      "XAU": 0.00054365
    },
    "2022-06-18": {
      "XAU": 0.00054365
    },
    "2022-06-19": {
      "XAU": 0.00054393
    },
    "2022-06-20": {
      "XAU": 0.00054429
    },
    "2022-06-21": {
      "XAU": 0.00054619
    },
    "2022-06-22": {
      "XAU": 0.00054426
    },
    "2022-06-23": {
      "XAU": 0.00054825
    },
    "2022-06-24": {
      "XAU": 0.00054728
    },
    "2022-06-25": {
      "XAU": 0.00054728
    },
    "2022-06-26": {
      "XAU": 0.00054614
    },
    "2022-06-27": {
      "XAU": 0.00054859
    },
    "2022-06-28": {
      "XAU": 0.00054987
    },
    "2022-06-29": {
      "XAU": 0.00054993
    },
    "2022-06-30": {
      "XAU": 0.00055377
    },
    "2022-07-01": {
      "XAU": 0.00055233
    },
    "2022-07-02": {
      "XAU": 0.00055233
    },
    "2022-07-03": {
      "XAU": 0.00055258
    },
    "2022-07-04": {
      "XAU": 0.00055286
    },
    "2022-07-05": {
      "XAU": 0.00056569
    },
    "2022-07-06": {
      "XAU": 0.00057483
    },
    "2022-07-07": {
      "XAU": 0.00057475
    },
    "2022-07-08": {
      "XAU": 0.00057391
    },
    "2022-07-09": {
      "XAU": 0.00057409
    },
    "2022-07-10": {
      "XAU": 0.00057341
    },
    "2022-07-11": {
      "XAU": 0.00057672
    },
    "2022-07-12": {
      "XAU": 0.00057935
    },
    "2022-07-13": {
      "XAU": 0.00057722
    },
    "2022-07-14": {
      "XAU": 0.00058445
    },
    "2022-07-15": {
      "XAU": 0.00058575
    },
    "2022-07-16": {
      "XAU": 0.00058559
    },
    "2022-07-17": {
      "XAU": 0.00058491
    },
    "2022-07-18": {
      "XAU": 0.00058531
    },
    "2022-07-19": {
      "XAU": 0.00058464
    },
    "2022-07-20": {
      "XAU": 0.00058979
    },
    "2022-07-21": {
      "XAU": 0.00058201
    },
    "2022-07-22": {
      "XAU": 0.00057882
    },
    "2022-07-23": {
      "XAU": 0.00057903
    },
    "2022-07-24": {
      "XAU": 0.00057992
    },
    "2022-07-25": {
      "XAU": 0.00058176
    },
    "2022-07-26": {
      "XAU": 0.00058202
    },
    "2022-07-27": {
      "XAU": 0.00057533
    },
    "2022-07-28": {
      "XAU": 0.00056975
    },
    "2022-07-29": {
      "XAU": 0.00056616
    },
    "2022-07-30": {
      "XAU": 0.00056616
    },
    "2022-07-31": {
      "XAU": 0.00056738
    },
    "2022-08-01": {
      "XAU": 0.00056438
    },
    "2022-08-02": {
      "XAU": 0.00056896
    },
    "2022-08-03": {
      "XAU": 0.00056686
    },
    "2022-08-04": {
      "XAU": 0.00055781
    },
    "2022-08-05": {
      "XAU": 0.00056342
    },
    "2022-08-06": {
      "XAU": 0.0005632
    },
    "2022-08-07": {
      "XAU": 0.0005635
    },
    "2022-08-08": {
      "XAU": 0.0005589
    },
    "2022-08-09": {
      "XAU": 0.00055748
    },
    "2022-08-10": {
      "XAU": 0.00055828
    },
    "2022-08-11": {
      "XAU": 0.0005594
    },
    "2022-08-12": {
      "XAU": 0.00055506
    },
    "2022-08-13": {
      "XAU": 0.00055485
    },
    "2022-08-14": {
      "XAU": 0.00055554
    },
    "2022-08-15": {
      "XAU": 0.00056204
    },
    "2022-08-16": {
      "XAU": 0.00056325
    },
    "2022-08-17": {
      "XAU": 0.00056698
    },
    "2022-08-18": {
      "XAU": 0.00056877
    },
    "2022-08-19": {
      "XAU": 0.0005724
    },
    "2022-08-20": {
      "XAU": 0.00057264
    },
    "2022-08-21": {
      "XAU": 0.00057255
    },
    "2022-08-22": {
      "XAU": 0.00057629
    },
    "2022-08-23": {
      "XAU": 0.00057284
    },
    "2022-08-24": {
      "XAU": 0.00057066
    },
    "2022-08-25": {
      "XAU": 0.00056928
    },
    "2022-08-26": {
      "XAU": 0.00057539
    },
    "2022-08-27": {
      "XAU": 0.00057536
    },
    "2022-08-28": {
      "XAU": 0.00057647
    },
    "2022-08-29": {
      "XAU": 0.00057554
    },
    "2022-08-30": {
      "XAU": 0.00058035
    },
    "2022-08-31": {
      "XAU": 0.00058516
    },
    "2022-09-01": {
      "XAU": 0.00058944
    },
    "2022-09-02": {
      "XAU": 0.000584
    },
    "2022-09-03": {
      "XAU": 0.00058409
    },
    "2022-09-04": {
      "XAU": 0.00058509
    },
    "2022-09-05": {
      "XAU": 0.00058372
    },
    "2022-09-06": {
      "XAU": 0.00058763
    },
    "2022-09-07": {
      "XAU": 0.00058249
    },
    "2022-09-08": {
      "XAU": 0.00058487
    },
    "2022-09-09": {
      "XAU": 0.00058242
    },
    "2022-09-10": {
      "XAU": 0.00058242
    },
    "2022-09-11": {
      "XAU": 0.00058242
    },
    "2022-09-12": {
      "XAU": 0.00057975
    },
    "2022-09-13": {
      "XAU": 0.00058752
    },
    "2022-09-14": {
      "XAU": 0.00058897
    },
    "2022-09-15": {
      "XAU": 0.0006015
    },
    "2022-09-16": {
      "XAU": 0.00059687
    },
    "2022-09-17": {
      "XAU": 0.00059711
    },
    "2022-09-18": {
      "XAU": 0.0005957
    },
    "2022-09-19": {
      "XAU": 0.00059679
    },
    "2022-09-20": {
      "XAU": 0.00060038
    },
    "2022-09-21": {
      "XAU": 0.00059854
    },
    "2022-09-22": {
      "XAU": 0.00059804
    },
    "2022-09-23": {
      "XAU": 0.00060864
    },
    "2022-09-24": {
      "XAU": 0.0006084
    },
    "2022-09-25": {
      "XAU": 0.00060826
    },
    "2022-09-26": {
      "XAU": 0.00060794
    },
    "2022-09-27": {
      "XAU": 0.000614
    },
    "2022-09-28": {
      "XAU": 0.00060322
    },
    "2022-09-29": {
      "XAU": 0.00060121
    },
    "2022-09-30": {
      "XAU": 0.00060207
    },
    "2022-10-01": {
      "XAU": 0.00060218
    },
    "2022-10-02": {
      "XAU": 0.00060132
    },
    "2022-10-03": {
      "XAU": 0.00058765
    },
    "2022-10-04": {
      "XAU": 0.00057974
    },
    "2022-10-05": {
      "XAU": 0.00058199
    },
    "2022-10-06": {
      "XAU": 0.00058449
    },
    "2022-10-07": {
      "XAU": 0.00058997
    },
    "2022-10-08": {
      "XAU": 0.00059005
    },
    "2022-10-09": {
      "XAU": 0.00058931
    },
    "2022-10-10": {
      "XAU": 0.00059902
    },
    "2022-10-11": {
      "XAU": 0.00060055
    },
    "2022-10-12": {
      "XAU": 0.00059719
    },
    "2022-10-13": {
      "XAU": 0.00060086
    },
    "2022-10-14": {
      "XAU": 0.00060839
    },
    "2022-10-15": {
      "XAU": 0.00060831
    },
    "2022-10-16": {
      "XAU": 0.00060731
    },
    "2022-10-17": {
      "XAU": 0.00060581
    },
    "2022-10-18": {
      "XAU": 0.00060501
    },
    "2022-10-19": {
      "XAU": 0.00061467
    },
    "2022-10-20": {
      "XAU": 0.00061498
    },
    "2022-10-21": {
      "XAU": 0.00060317
    },
    "2022-10-22": {
      "XAU": 0.00060327
    },
    "2022-10-23": {
      "XAU": 0.00060353
    },
    "2022-10-24": {
      "XAU": 0.00060546
    },
    "2022-10-25": {
      "XAU": 0.00060545
    },
    "2022-10-26": {
      "XAU": 0.00060063
    },
    "2022-10-27": {
      "XAU": 0.00060137
    },
    "2022-10-28": {
      "XAU": 0.00060808
    },
    "2022-10-29": {
      "XAU":0.00060813
    }
  }
}